{
    "AllVideos": {
        "url": "https://translations.telegram.org/en/android_x/camera_and_media/AllVideos",
        "photo_url": "https://telegra.ph/file/p/2ffab6ccf0f/be83e76080ac335addb5517.jpg?c=103,103,280,280,280,280",
        "has_binding": true,
        "values": {
            "singular": "All videos"
        }
    },
    "VideoTrimUnsupported": {
        "url": "https://translations.telegram.org/en/android_x/camera_and_media/VideoTrimUnsupported",
        "photo_url": "https://telegra.ph/file/p/dd95efb8959/404c110a8c5716bdacdcd17.jpg?c=10,790,386,386,280,280",
        "has_binding": false,
        "values": {
            "singular": "This video file could not be trimmed"
        }
    },
    "ViewMessagesFromYou": {
        "url": "https://translations.telegram.org/en/android_x/camera_and_media/ViewMessagesFromYou",
        "photo_url": "https://telegra.ph/file/p/e7994f4aff0/472f8f93071dc35e1b9141d.jpg?c=95,933,341,341,280,280",
        "has_binding": false,
        "values": {
            "singular": "Messages from you"
        }
    }
}