{
    "AddFolderAndJoinXChats": {
        "url": "https://translations.telegram.org/en/android_x/general/AddFolderAndJoinXChats",
        "photo_url": "https://telegra.ph/file/p/4d73c687cb6/b42bf9977308d8765bfca17.jpg?c=88,899,424,424,280,280",
        "has_binding": false,
        "values": {
            "singular": "Add Folder and Join <mark class=\"token\">%1$s</mark> chat",
            "plural": "Add Folder and Join <mark class=\"token\">%1$s</mark> chats"
        }
    },
    "AppUpdateAvailableVersionPrompt": {
        "url": "https://translations.telegram.org/en/android_x/general/AppUpdateAvailableVersionPrompt",
        "photo_url": "https://telegra.ph/file/p/8bcc9f79aa6/8ea2b55fc114a2ef4839f17.jpg?c=0,501,600,615,272,280",
        "has_binding": false,
        "values": {
            "singular": "A new **Telegram X** `<mark class=\"token\">%2$s</mark>` update is available. Would you like to download? (<mark class=\"token\">%1$s</mark>)"
        }
    },
    "AppUpdateInstall": {
        "url": "https://translations.telegram.org/en/android_x/general/AppUpdateInstall",
        "photo_url": "https://telegra.ph/file/p/5793047cbef/e40c3333984ae4601a58b17.jpg?c=313,885,280,280,280,280",
        "has_binding": false,
        "values": {
            "singular": "Update"
        }
    },
    "AppUpdateReady": {
        "url": "https://translations.telegram.org/en/android_x/general/AppUpdateReady",
        "photo_url": "https://telegra.ph/file/p/5793047cbef/e40c3333984ae4601a58b17.jpg?c=4,715,459,459,280,280",
        "has_binding": false,
        "values": {
            "singular": "Telegram X is ready to be updated."
        }
    },
    "AreChoosingSticker": {
        "url": "https://translations.telegram.org/en/android_x/general/AreChoosingSticker",
        "photo_url": "https://telegra.ph/file/p/f7fea162c1e/c03cab4577386fbc43fa419.jpg?c=162,17,419,419,280,280",
        "has_binding": false,
        "values": {
            "singular": "<mark class=\"token\">%1$s</mark> are choosing stickers"
        }
    },
    "AttachVideoNoteExpired": {
        "url": "https://translations.telegram.org/en/android_x/general/AttachVideoNoteExpired",
        "photo_url": "https://telegra.ph/file/p/0ce88bf814e/1a5c9bf6f7785da93155e17.jpg?c=156,972,289,289,280,280",
        "has_binding": true,
        "values": {
            "singular": "Expired video message"
        }
    },
    "AttachVoiceNoteExpired": {
        "url": "https://translations.telegram.org/en/android_x/general/AttachVoiceNoteExpired",
        "photo_url": "https://telegra.ph/file/p/0ce88bf814e/1a5c9bf6f7785da93155e17.jpg?c=157,924,288,288,280,280",
        "has_binding": true,
        "values": {
            "singular": "Expired voice message"
        }
    },
    "AudioPlaybackError": {
        "url": "https://translations.telegram.org/en/android_x/general/AudioPlaybackError",
        "photo_url": "https://telegra.ph/file/p/0d30249c019/f40fecb6b6e098eb1188d17.jpg?c=64,6,434,434,280,280",
        "has_binding": false,
        "values": {
            "singular": "Failed to play audio, see logs for details."
        }
    },
    "CallMessageOutgoingMissed": {
        "url": "https://translations.telegram.org/en/android_x/general/CallMessageOutgoingMissed",
        "photo_url": "https://telegra.ph/file/p/8c05c999e28/aed25cf507b36441aabab1d.jpg?c=254,879,280,280,280,280",
        "has_binding": true,
        "values": {
            "singular": "Canceled Call"
        }
    },
    "Cancelled": {
        "url": "https://translations.telegram.org/en/android_x/general/Cancelled",
        "photo_url": "https://telegra.ph/file/p/c30a09d584a/1b18dab0dbe311531a2511d.jpg?c=140,440,280,280,280,280",
        "has_binding": false,
        "values": {
            "singular": "Canceled"
        }
    },
    "ChatBackgroundView": {
        "url": "https://translations.telegram.org/en/android_x/general/ChatBackgroundView",
        "photo_url": "https://telegra.ph/file/p/f56474a92d1/4457ca48550bd16fe863117.jpg?c=114,509,364,364,280,280",
        "has_binding": true,
        "values": {
            "singular": "View Wallpaper"
        }
    },
    "ChatContentChannelTtlDays": {
        "url": "https://translations.telegram.org/en/android_x/general/ChatContentChannelTtlDays",
        "photo_url": "https://telegra.ph/file/p/748fd83ff10/3a78d566f3008d204784217.jpg?c=92,107,405,405,280,280",
        "has_binding": false,
        "values": {
            "singular": "Set posts to auto-delete in <mark class=\"token\">%1$s</mark> day",
            "plural": "Set posts to auto-delete in <mark class=\"token\">%1$s</mark> days"
        }
    },
    "ChatContentChannelTtlMonths": {
        "url": "https://translations.telegram.org/en/android_x/general/ChatContentChannelTtlMonths",
        "photo_url": "https://telegra.ph/file/p/9dfce12c633/b59ce5ca0bb0170be95d217.jpg?c=104,187,407,407,280,280",
        "has_binding": false,
        "values": {
            "singular": "Set posts to auto-delete in <mark class=\"token\">%1$s</mark> month",
            "plural": "Set posts to auto-delete in <mark class=\"token\">%1$s</mark> months"
        }
    },
    "ChatContentChannelTtlOff": {
        "url": "https://translations.telegram.org/en/android_x/general/ChatContentChannelTtlOff",
        "photo_url": "https://telegra.ph/file/p/9dfce12c633/b59ce5ca0bb0170be95d217.jpg?c=112,114,352,352,280,280",
        "has_binding": false,
        "values": {
            "singular": "Disabled auto-delete"
        }
    },
    "ChatContentChannelTtlWeeks": {
        "url": "https://translations.telegram.org/en/android_x/general/ChatContentChannelTtlWeeks",
        "photo_url": "https://telegra.ph/file/p/748fd83ff10/3a78d566f3008d204784217.jpg?c=106,191,394,394,280,280",
        "has_binding": false,
        "values": {
            "singular": "Set posts to auto-delete in <mark class=\"token\">%1$s</mark> week",
            "plural": "Set posts to auto-delete in <mark class=\"token\">%1$s</mark> weeks"
        }
    },
    "ChatContentGroupTtlDays": {
        "url": "https://translations.telegram.org/en/android_x/general/ChatContentGroupTtlDays",
        "photo_url": "https://telegra.ph/file/p/15171568899/56df73661a5d4d58b5fda17.jpg?c=98,197,440,440,280,280",
        "has_binding": false,
        "values": {
            "singular": "Set messages to auto-delete in <mark class=\"token\">%1$s</mark> day",
            "plural": "Set messages to auto-delete in <mark class=\"token\">%1$s</mark> days"
        }
    },
    "ChatContentGroupTtlMonths": {
        "url": "https://translations.telegram.org/en/android_x/general/ChatContentGroupTtlMonths",
        "photo_url": "https://telegra.ph/file/p/1bba6ccc826/a56cffdf41904174a8ef617.jpg?c=79,187,477,477,280,280",
        "has_binding": false,
        "values": {
            "singular": "Set messages to auto-delete in <mark class=\"token\">%1$s</mark> month",
            "plural": "Set messages to auto-delete in <mark class=\"token\">%1$s</mark> months"
        }
    },
    "ChatContentGroupTtlOff": {
        "url": "https://translations.telegram.org/en/android_x/general/ChatContentGroupTtlOff",
        "photo_url": "https://telegra.ph/file/p/1bba6ccc826/a56cffdf41904174a8ef617.jpg?c=112,304,351,351,280,280",
        "has_binding": false,
        "values": {
            "singular": "Disabled auto-delete"
        }
    },
    "ChatContentGroupTtlWeeks": {
        "url": "https://translations.telegram.org/en/android_x/general/ChatContentGroupTtlWeeks",
        "photo_url": "https://telegra.ph/file/p/15171568899/56df73661a5d4d58b5fda17.jpg?c=97,272,447,447,280,280",
        "has_binding": false,
        "values": {
            "singular": "Set messages to auto-delete in <mark class=\"token\">%1$s</mark> week",
            "plural": "Set messages to auto-delete in <mark class=\"token\">%1$s</mark> weeks"
        }
    },
    "ChatContentTtlDays": {
        "url": "https://translations.telegram.org/en/android_x/general/ChatContentTtlDays",
        "photo_url": "https://telegra.ph/file/p/8eb0f8c1adf/1f16630cfd044b4f1f74517.jpg?c=92,105,418,418,280,280",
        "has_binding": false,
        "values": {
            "singular": "Set the self-destruct timer to <mark class=\"token\">%1$s</mark> day",
            "plural": "Set the self-destruct timer to <mark class=\"token\">%1$s</mark> days"
        }
    },
    "ChatContentTtlHours": {
        "url": "https://translations.telegram.org/en/android_x/general/ChatContentTtlHours",
        "photo_url": "https://telegra.ph/file/p/579c2a098a1/2d43139a97e1f1ea8bc0517.jpg?c=103,105,413,413,280,280",
        "has_binding": false,
        "values": {
            "singular": "Set the self-destruct timer to <mark class=\"token\">%1$s</mark> hour",
            "plural": "Set the self-destruct timer to <mark class=\"token\">%1$s</mark> hours"
        }
    },
    "ChatContentTtlMinutes": {
        "url": "https://translations.telegram.org/en/android_x/general/ChatContentTtlMinutes",
        "photo_url": "https://telegra.ph/file/p/1c53432aac3/6b5900ef5bb10cfcf9b3517.jpg?c=98,102,440,440,280,280",
        "has_binding": false,
        "values": {
            "singular": "Set the self-destruct timer to <mark class=\"token\">%1$s</mark> minute",
            "plural": "Set the self-destruct timer to <mark class=\"token\">%1$s</mark> minutes"
        }
    },
    "ChatContentTtlSeconds": {
        "url": "https://translations.telegram.org/en/android_x/general/ChatContentTtlSeconds",
        "photo_url": "https://telegra.ph/file/p/41c5d2aee0b/7f03d511a17a52590c4ee17.jpg?c=97,101,443,443,280,280",
        "has_binding": false,
        "values": {
            "singular": "Set the self-destruct timer to <mark class=\"token\">%1$s</mark> second",
            "plural": "Set the self-destruct timer to <mark class=\"token\">%1$s</mark> seconds"
        }
    },
    "ChatContentTtlWeeks": {
        "url": "https://translations.telegram.org/en/android_x/general/ChatContentTtlWeeks",
        "photo_url": "https://telegra.ph/file/p/8eb0f8c1adf/1f16630cfd044b4f1f74517.jpg?c=101,499,422,422,280,280",
        "has_binding": false,
        "values": {
            "singular": "Set the self-destruct timer to <mark class=\"token\">%1$s</mark> week",
            "plural": "Set the self-destruct timer to <mark class=\"token\">%1$s</mark> weeks"
        }
    },
    "ChatFolderInviteLinkChatTypesNotSupported": {
        "url": "https://translations.telegram.org/en/android_x/general/ChatFolderInviteLinkChatTypesNotSupported",
        "photo_url": "https://telegra.ph/file/p/31576a4116d/a327fbebfd8e6db99bc6417.jpg?c=41,610,516,516,280,280",
        "has_binding": true,
        "values": {
            "singular": "You can’t share folders which include or exclude specific chat types like **Groups**, **Contacts**, etc."
        }
    },
    "ChatFolderInviteLinkInfo": {
        "url": "https://translations.telegram.org/en/android_x/general/ChatFolderInviteLinkInfo",
        "photo_url": "https://telegra.ph/file/p/733f14a89a7/954839eb2e30b7d04952217.jpg?c=0,228,594,599,278,280",
        "has_binding": true,
        "values": {
            "singular": "Anyone with this link can add <mark class=\"token\">%2$s</mark> folder and the <mark class=\"token\">%1$s</mark> chat selected below.",
            "plural": "Anyone with this link can add <mark class=\"token\">%2$s</mark> folder and the <mark class=\"token\">%1$s</mark> chats selected below."
        }
    },
    "ChatFolderInviteLinkInfoNoCounter": {
        "url": "https://translations.telegram.org/en/android_x/general/ChatFolderInviteLinkInfoNoCounter",
        "photo_url": "https://telegra.ph/file/p/2c2494b4542/7f32971c5e6b67d60092117.jpg?c=0,212,600,651,258,280",
        "has_binding": false,
        "values": {
            "singular": "Anyone with this link can add <mark class=\"token\">%1$s</mark> folder and the chats selected below."
        }
    },
    "ChatFolderInviteLinkJoinChatsHint": {
        "url": "https://translations.telegram.org/en/android_x/general/ChatFolderInviteLinkJoinChatsHint",
        "photo_url": "https://telegra.ph/file/p/4d73c687cb6/b42bf9977308d8765bfca17.jpg?c=0,175,588,592,278,280",
        "has_binding": true,
        "values": {
            "singular": "You can deselect the chats you don’t want to join."
        }
    },
    "ChatFolderInviteLinkLeaveChatsHint": {
        "url": "https://translations.telegram.org/en/android_x/general/ChatFolderInviteLinkLeaveChatsHint",
        "photo_url": "https://telegra.ph/file/p/2594b1c5b7e/0a5a884244a79cf5c159417.jpg?c=0,170,600,610,274,280",
        "has_binding": false,
        "values": {
            "singular": "You can deselect the chats you don’t want to leave."
        }
    },
    "ChatFolderInviteLinkNameHint": {
        "url": "https://translations.telegram.org/en/android_x/general/ChatFolderInviteLinkNameHint",
        "photo_url": "https://telegra.ph/file/p/733f14a89a7/954839eb2e30b7d04952217.jpg?c=64,159,280,280,280,280",
        "has_binding": false,
        "values": {
            "singular": "Name"
        }
    },
    "ChatFolderInviteLinkNoChatsToShare": {
        "url": "https://translations.telegram.org/en/android_x/general/ChatFolderInviteLinkNoChatsToShare",
        "photo_url": "https://telegra.ph/file/p/8bcf12b48bf/46eecee6026478feb7e2817.jpg?c=0,74,600,610,276,280",
        "has_binding": true,
        "values": {
            "singular": "There are no chats in this folder that you can share with others."
        }
    },
    "ChatFolderInviteLinkNoChatsToShareHeader": {
        "url": "https://translations.telegram.org/en/android_x/general/ChatFolderInviteLinkNoChatsToShareHeader",
        "photo_url": "https://telegra.ph/file/p/8bcf12b48bf/46eecee6026478feb7e2817.jpg?c=10,170,372,372,280,280",
        "has_binding": true,
        "values": {
            "singular": "These chats cannot be shared"
        }
    },
    "ChatFolderInviteLinkNoChatsToShareInfo": {
        "url": "https://translations.telegram.org/en/android_x/general/ChatFolderInviteLinkNoChatsToShareInfo",
        "photo_url": "https://telegra.ph/file/p/8bcf12b48bf/46eecee6026478feb7e2817.jpg?c=0,213,600,642,262,280",
        "has_binding": true,
        "values": {
            "singular": "You can only share groups and channels in which you are allowed to create invite links."
        }
    },
    "ChatFolderInviteLinkSelectGroupsAndChannelsInfo": {
        "url": "https://translations.telegram.org/en/android_x/general/ChatFolderInviteLinkSelectGroupsAndChannelsInfo",
        "photo_url": "https://telegra.ph/file/p/2c2494b4542/7f32971c5e6b67d60092117.jpg?c=5,425,505,505,280,280",
        "has_binding": false,
        "values": {
            "singular": "Select groups and channels that you want everyone who adds this folder to join."
        }
    },
    "ChatFolderInviteLinksInfo": {
        "url": "https://translations.telegram.org/en/android_x/general/ChatFolderInviteLinksInfo",
        "photo_url": "https://telegra.ph/file/p/04f7bbd1b6f/b7e73550ffcbfedb1e82c17.jpg?c=0,520,582,585,278,280",
        "has_binding": true,
        "values": {
            "singular": "Share access to some of this folder’s groups and channels with others."
        }
    },
    "ChatFolderSaveChangesBeforeCreatingANewInviteLink": {
        "url": "https://translations.telegram.org/en/android_x/general/ChatFolderSaveChangesBeforeCreatingANewInviteLink",
        "photo_url": "https://telegra.ph/file/p/522d38096f5/de4c8731b8a66dab9238c17.jpg?c=0,638,600,607,278,280",
        "has_binding": false,
        "values": {
            "singular": "Changes must be saved before creating a new link"
        }
    },
    "ChatFoldersSetupSuggestionAction": {
        "url": "https://translations.telegram.org/en/android_x/general/ChatFoldersSetupSuggestionAction",
        "photo_url": "https://telegra.ph/file/p/8bbbafde819/2191c66bfe7df9678d8c019.jpg?c=352,1844,497,497,280,280",
        "has_binding": false,
        "values": {
            "singular": "Start setting up"
        }
    },
    "ChatFoldersSetupSuggestionText": {
        "url": "https://translations.telegram.org/en/android_x/general/ChatFoldersSetupSuggestionText",
        "photo_url": "https://telegra.ph/file/p/8bbbafde819/2191c66bfe7df9678d8c019.jpg?c=0,987,1200,1268,266,280",
        "has_binding": false,
        "values": {
            "singular": "The wait is over. **Chat Folders** are here for everyone to enjoy… and **customize**.<br/><br/>Prefer icons? We’ve got you covered. Bottom tabs? No problem. Filter chats inside a folder? Swipe tab to access it as well.<br/><br/>Archive as folder, hiding tabs, marking folder as read, sharing folders, and more features are now available."
        }
    },
    "ChatFoldersSetupSuggestionTitle": {
        "url": "https://translations.telegram.org/en/android_x/general/ChatFoldersSetupSuggestionTitle",
        "photo_url": "https://telegra.ph/file/p/8bbbafde819/2191c66bfe7df9678d8c019.jpg?c=33,1196,509,509,280,280",
        "has_binding": false,
        "values": {
            "singular": "Folders are here!"
        }
    },
    "ChoosingSticker": {
        "url": "https://translations.telegram.org/en/android_x/general/ChoosingSticker",
        "photo_url": "https://telegra.ph/file/p/6b1ffc95f5e/0c6a90173171c0868c7b717.jpg?c=140,55,280,280,280,280",
        "has_binding": false,
        "values": {
            "singular": "choosing a sticker"
        }
    },
    "ClearHistory": {
        "url": "https://translations.telegram.org/en/android_x/general/ClearHistory",
        "photo_url": "https://telegra.ph/file/p/65799d8ab70/aa060fdde2e598d5d40331d.jpg?c=398,178,280,280,280,280",
        "has_binding": true,
        "values": {
            "singular": "Clear history"
        }
    },
    "CopiedBankCard": {
        "url": "https://translations.telegram.org/en/android_x/general/CopiedBankCard",
        "photo_url": "https://telegra.ph/file/p/33094c7f77f/fcd98646b5c0ec776e5d917.jpg?c=42,333,515,515,280,280",
        "has_binding": false,
        "values": {
            "singular": "Card number copied to the clipboard"
        }
    },
    "CopyBankCard": {
        "url": "https://translations.telegram.org/en/android_x/general/CopyBankCard",
        "photo_url": "https://telegra.ph/file/p/5c86a2f5ace/f285908886f52222bd41317.jpg?c=78,886,280,280,280,280",
        "has_binding": false,
        "values": {
            "singular": "Copy card number"
        }
    },
    "CopyLink": {
        "url": "https://translations.telegram.org/en/android_x/general/CopyLink",
        "photo_url": "https://telegra.ph/file/p/308a67939e4/894c7aa9f39d8a6622a851d.jpg?c=90,920,280,280,280,280",
        "has_binding": true,
        "values": {
            "singular": "Copy link"
        }
    },
    "CreateANewLink": {
        "url": "https://translations.telegram.org/en/android_x/general/CreateANewLink",
        "photo_url": "https://telegra.ph/file/p/a77acc55018/04000a4a786dd5b103e8e17.jpg?c=85,653,280,280,280,280",
        "has_binding": false,
        "values": {
            "singular": "Create a New Link"
        }
    },
    "CreateAnInviteLink": {
        "url": "https://translations.telegram.org/en/android_x/general/CreateAnInviteLink",
        "photo_url": "https://telegra.ph/file/p/04f7bbd1b6f/b7e73550ffcbfedb1e82c17.jpg?c=90,652,280,280,280,280",
        "has_binding": false,
        "values": {
            "singular": "Create an Invite Link"
        }
    },
    "CreateLink": {
        "url": "https://translations.telegram.org/en/android_x/general/CreateLink",
        "photo_url": "https://telegra.ph/file/p/0e34f9c3182/526266e6f42580cca799a1d.jpg?c=113,630,305,305,280,280",
        "has_binding": true,
        "values": {
            "singular": "Create Link"
        }
    },
    "DeleteAndStop": {
        "url": "https://translations.telegram.org/en/android_x/general/DeleteAndStop",
        "photo_url": "https://telegra.ph/file/p/58377c649e5/ca02d62f90adf7ffcf6eb17.jpg?c=59,825,280,280,280,280",
        "has_binding": true,
        "values": {
            "singular": "Delete and Block"
        }
    },
    "DeleteAndStopRepliesConfirm": {
        "url": "https://translations.telegram.org/en/android_x/general/DeleteAndStopRepliesConfirm",
        "photo_url": "https://telegra.ph/file/p/58377c649e5/ca02d62f90adf7ffcf6eb17.jpg?c=0,470,600,653,258,280",
        "has_binding": false,
        "values": {
            "singular": "Are you sure you want to delete all **reply notifications** and stop receiving them?"
        }
    },
    "DeleteFolder": {
        "url": "https://translations.telegram.org/en/android_x/general/DeleteFolder",
        "photo_url": "https://telegra.ph/file/p/107effb0b65/94baf0b5d9b7f824b26d517.jpg?c=160,1038,280,280,280,280",
        "has_binding": false,
        "values": {
            "singular": "Delete Folder"
        }
    },
    "DeleteFolderAndLeaveXChats": {
        "url": "https://translations.telegram.org/en/android_x/general/DeleteFolderAndLeaveXChats",
        "photo_url": "https://telegra.ph/file/p/2594b1c5b7e/0a5a884244a79cf5c159417.jpg?c=57,839,485,485,280,280",
        "has_binding": false,
        "values": {
            "singular": "Delete Folder and Leave <mark class=\"token\">%1$s</mark> chat",
            "plural": "Delete Folder and Leave <mark class=\"token\">%1$s</mark> chats"
        }
    },
    "DeleteFolderWithInviteLinksConfirm": {
        "url": "https://translations.telegram.org/en/android_x/general/DeleteFolderWithInviteLinksConfirm",
        "photo_url": "https://telegra.ph/file/p/ef2cd90e9ce/2aee35f4eb41b584f552e17.jpg?c=0,588,600,657,256,280",
        "has_binding": true,
        "values": {
            "singular": "Are you sure you want to delete this folder? This will also **deactivate all the invite links** created to share this folder."
        }
    },
    "DidNotGetTheCode": {
        "url": "https://translations.telegram.org/en/android_x/general/DidNotGetTheCode",
        "photo_url": "https://telegra.ph/file/p/4f7ca9d0d2f/f26c955e07d71b051ba6d19.jpg?c=17,801,625,625,280,280",
        "has_binding": true,
        "values": {
            "singular": "Didn't get the code?"
        }
    },
    "DismissAllPinned": {
        "url": "https://translations.telegram.org/en/android_x/general/DismissAllPinned",
        "photo_url": "https://telegra.ph/file/p/b29ff99b5d2/ab1ae62888be1098b8c7217.jpg?c=139,846,324,324,280,280",
        "has_binding": false,
        "values": {
            "singular": "Dismiss All Messages"
        }
    },
    "DoNotAddFolder": {
        "url": "https://translations.telegram.org/en/android_x/general/DoNotAddFolder",
        "photo_url": "https://telegra.ph/file/p/d41d907d158/139e3f0ee45723ebb8a9f17.jpg?c=156,1029,289,289,280,280",
        "has_binding": false,
        "values": {
            "singular": "Do not add folder"
        }
    },
    "DownloadUpdate": {
        "url": "https://translations.telegram.org/en/android_x/general/DownloadUpdate",
        "photo_url": "https://telegra.ph/file/p/8bcc9f79aa6/8ea2b55fc114a2ef4839f17.jpg?c=66,825,280,280,280,280",
        "has_binding": false,
        "values": {
            "singular": "Download update"
        }
    },
    "DownloadedXFiles": {
        "url": "https://translations.telegram.org/en/android_x/general/DownloadedXFiles",
        "photo_url": "https://telegra.ph/file/p/0a89ed4dc9e/cf9e870aac9da64984fce17.jpg?c=21,555,558,558,280,280",
        "has_binding": false,
        "values": {
            "singular": "Successfully downloaded <mark class=\"token\">%1$s</mark> file:<br/><mark class=\"token\">%2$s</mark>",
            "plural": "Successfully downloaded <mark class=\"token\">%1$s</mark> files:<br/><mark class=\"token\">%2$s</mark>"
        }
    },
    "DraftPreFillWarning": {
        "url": "https://translations.telegram.org/en/android_x/general/DraftPreFillWarning",
        "photo_url": "https://telegra.ph/file/p/add29ebdb79/8a9567c54c87d908ee92317.jpg?c=0,594,600,655,256,280",
        "has_binding": false,
        "values": {
            "singular": "Your previous draft message in this chat is about to be replaced."
        }
    },
    "EventLogSlowModeChangedYou": {
        "url": "https://translations.telegram.org/en/android_x/general/EventLogSlowModeChangedYou",
        "photo_url": "https://telegra.ph/file/p/b591af0fa4b/1b2251e8f1b0827d6341217.jpg?c=73,467,462,462,280,280",
        "has_binding": false,
        "values": {
            "singular": "You set the slow mode timer to <mark class=\"token\">%1$s</mark>"
        }
    },
    "ExperimentalBuildInfo": {
        "url": "https://translations.telegram.org/en/android_x/general/ExperimentalBuildInfo",
        "photo_url": "https://telegra.ph/file/p/2ca725e9982/e7a3301f18d6a9433e23e17.jpg?c=0,0,598,441,280,204",
        "has_binding": false,
        "values": {
            "singular": "This version of **Telegram X** is not designed for long-term use.<br/><br/>It may completely stop working over a time and you cannot turn notifications on.<br/><br/>If you are looking for the proper Telegram X APK file, see https://t.me/tgx_log"
        }
    },
    "ExperimentalBuildTitle": {
        "url": "https://translations.telegram.org/en/android_x/general/ExperimentalBuildTitle",
        "photo_url": "https://telegra.ph/file/p/2ca725e9982/e7a3301f18d6a9433e23e17.jpg?c=21,0,433,428,280,278",
        "has_binding": false,
        "values": {
            "singular": "Caution: experimental build"
        }
    },
    "FolderLink": {
        "url": "https://translations.telegram.org/en/android_x/general/FolderLink",
        "photo_url": "https://telegra.ph/file/p/2c2494b4542/7f32971c5e6b67d60092117.jpg?c=67,262,280,280,280,280",
        "has_binding": false,
        "values": {
            "singular": "Folder Link"
        }
    },
    "FolderVisible": {
        "url": "https://translations.telegram.org/en/android_x/general/FolderVisible",
        "photo_url": "https://telegra.ph/file/p/04f7bbd1b6f/b7e73550ffcbfedb1e82c17.jpg?c=10,237,280,280,280,280",
        "has_binding": false,
        "values": {
            "singular": "Folder visible"
        }
    },
    "ForwardAuthorImported": {
        "url": "https://translations.telegram.org/en/android_x/general/ForwardAuthorImported",
        "photo_url": "https://telegra.ph/file/p/7ecd9c899dc/9252bcef18e1f8688045517.jpg?c=3,74,506,506,280,280",
        "has_binding": true,
        "values": {
            "singular": "This message was imported from another app. It may not be real."
        }
    },
    "GiveawayAllWinnersReceivedLinks": {
        "url": "https://translations.telegram.org/en/android_x/general/GiveawayAllWinnersReceivedLinks",
        "photo_url": "https://telegra.ph/file/p/c8e8ba381de/fb876e38f930eee57a18917.jpg?c=75,725,473,473,280,280",
        "has_binding": true,
        "values": {
            "singular": "All winners received gift links in private messages."
        }
    },
    "GiveawayLearnMore": {
        "url": "https://translations.telegram.org/en/android_x/general/GiveawayLearnMore",
        "photo_url": "https://telegra.ph/file/p/c8e8ba381de/fb876e38f930eee57a18917.jpg?c=174,948,280,280,280,280",
        "has_binding": true,
        "values": {
            "singular": "Learn More"
        }
    },
    "GroupPrivate": {
        "url": "https://translations.telegram.org/en/android_x/general/GroupPrivate",
        "photo_url": "https://telegra.ph/file/p/d754914b945/151067ad4959a4710f1d517.jpg?c=72,554,280,280,280,280",
        "has_binding": false,
        "values": {
            "singular": "Private Group"
        }
    },
    "GroupPublic": {
        "url": "https://translations.telegram.org/en/android_x/general/GroupPublic",
        "photo_url": "https://telegra.ph/file/p/d754914b945/151067ad4959a4710f1d517.jpg?c=71,633,280,280,280,280",
        "has_binding": false,
        "values": {
            "singular": "Public Group"
        }
    },
    "ImportedSign": {
        "url": "https://translations.telegram.org/en/android_x/general/ImportedSign",
        "photo_url": "https://telegra.ph/file/p/7ecd9c899dc/9252bcef18e1f8688045517.jpg?c=188,499,280,280,280,280",
        "has_binding": true,
        "values": {
            "singular": "imported"
        }
    },
    "Initializing": {
        "url": "https://translations.telegram.org/en/android_x/general/Initializing",
        "photo_url": "https://telegra.ph/file/p/e0811bfd039/cf8d39265598df89bbc2d17.jpg?c=172,3,280,280,280,280",
        "has_binding": false,
        "values": {
            "singular": "Starting up…"
        }
    },
    "InviteLinkAdminName": {
        "url": "https://translations.telegram.org/en/android_x/general/InviteLinkAdminName",
        "photo_url": "https://telegra.ph/file/p/733f14a89a7/954839eb2e30b7d04952217.jpg?c=84,128,280,280,280,280",
        "has_binding": true,
        "values": {
            "singular": "Link Name (optional)"
        }
    },
    "IsChoosingSticker": {
        "url": "https://translations.telegram.org/en/android_x/general/IsChoosingSticker",
        "photo_url": "https://telegra.ph/file/p/61b64c1eb10/a7804ae38c4ed15027cdc17.jpg?c=154,49,356,356,280,280",
        "has_binding": false,
        "values": {
            "singular": "<mark class=\"token\">%1$s</mark> is choosing a sticker"
        }
    },
    "IsRecordingRound": {
        "url": "https://translations.telegram.org/en/android_x/general/IsRecordingRound",
        "photo_url": "https://telegra.ph/file/p/c7b900c447c/a3b4af8ee5da1e797cc6919.jpg?c=333,54,548,548,280,280",
        "has_binding": false,
        "values": {
            "singular": "<mark class=\"token\">%1$s</mark> is recording a video message"
        }
    },
    "JoinXChats": {
        "url": "https://translations.telegram.org/en/android_x/general/JoinXChats",
        "photo_url": "https://telegra.ph/file/p/f7168df461d/ae0de641450e8e04c5ed817.jpg?c=160,1038,280,280,280,280",
        "has_binding": false,
        "values": {
            "singular": "Join <mark class=\"token\">%1$s</mark> chat",
            "plural": "Join <mark class=\"token\">%1$s</mark> chats"
        }
    },
    "LaunchAppGuideFatalError": {
        "url": "https://translations.telegram.org/en/android_x/general/LaunchAppGuideFatalError",
        "photo_url": "https://telegra.ph/file/p/e0811bfd039/cf8d39265598df89bbc2d17.jpg?c=0,179,600,644,262,280",
        "has_binding": false,
        "values": {
            "singular": "Telegram X has closed unexpectedly the last time you were using it.<br/><br/>Press **Launch App** to try again."
        }
    },
    "LaunchSubtitleFatalError": {
        "url": "https://translations.telegram.org/en/android_x/general/LaunchSubtitleFatalError",
        "photo_url": "https://telegra.ph/file/p/e0811bfd039/cf8d39265598df89bbc2d17.jpg?c=71,70,280,280,280,280",
        "has_binding": false,
        "values": {
            "singular": "Unexpected error"
        }
    },
    "LinkPreviewEnlarged": {
        "url": "https://translations.telegram.org/en/android_x/general/LinkPreviewEnlarged",
        "photo_url": "https://telegra.ph/file/p/dab829addc1/458cb270b58233eea043b17.jpg?c=177,349,410,410,280,280",
        "has_binding": false,
        "values": {
            "singular": "Link preview media will be enlarged"
        }
    },
    "LinkPreviewMinimized": {
        "url": "https://translations.telegram.org/en/android_x/general/LinkPreviewMinimized",
        "photo_url": "https://telegra.ph/file/p/34b10fdf773/7b0164d15de6c93320b7717.jpg?c=159,341,428,428,280,280",
        "has_binding": false,
        "values": {
            "singular": "Link preview media will be minimized"
        }
    },
    "LinkPreviewShowAbove": {
        "url": "https://translations.telegram.org/en/android_x/general/LinkPreviewShowAbove",
        "photo_url": "https://telegra.ph/file/p/45e046baffb/094ce8182cc5593a2ac6717.jpg?c=143,356,446,446,280,280",
        "has_binding": false,
        "values": {
            "singular": "Link preview will appear above the text"
        }
    },
    "LinkPreviewShowBelow": {
        "url": "https://translations.telegram.org/en/android_x/general/LinkPreviewShowBelow",
        "photo_url": "https://telegra.ph/file/p/bd8a561b6fb/117a9aa034c5879b3aeff17.jpg?c=143,679,445,445,280,280",
        "has_binding": false,
        "values": {
            "singular": "Link preview will appear below the text"
        }
    },
    "MarkFolderAsRead": {
        "url": "https://translations.telegram.org/en/android_x/general/MarkFolderAsRead",
        "photo_url": "https://telegra.ph/file/p/2e68df4c920/0b575922a12bd1679703f17.jpg?c=73,957,280,280,280,280",
        "has_binding": false,
        "values": {
            "singular": "Mark Folder as Read"
        }
    },
    "MediaFeatureUnavailable": {
        "url": "https://translations.telegram.org/en/android_x/general/MediaFeatureUnavailable",
        "photo_url": "https://telegra.ph/file/p/455be662040/94efd74261c48272155a517.jpg?c=105,727,483,483,280,280",
        "has_binding": false,
        "values": {
            "singular": "Feature is not available for this type of media"
        }
    },
    "MediaHapticForward": {
        "url": "https://translations.telegram.org/en/android_x/general/MediaHapticForward",
        "photo_url": "https://telegra.ph/file/p/7019ec53be6/eb44c7d26ba26c043a0bf17.jpg?c=221,783,280,280,280,280",
        "has_binding": false,
        "values": {
            "singular": "Forward"
        }
    },
    "MessageInputEmpty": {
        "url": "https://translations.telegram.org/en/android_x/general/MessageInputEmpty",
        "photo_url": "https://telegra.ph/file/p/90f48c4f562/036984ce7feb0dc39dbcc17.jpg?c=286,471,301,301,280,280",
        "has_binding": false,
        "values": {
            "singular": "Message cannot be empty"
        }
    },
    "MessagePinAlbum": {
        "url": "https://translations.telegram.org/en/android_x/general/MessagePinAlbum",
        "photo_url": "https://telegra.ph/file/p/c0bb39c954b/183fb612e01c8c39e063b17.jpg?c=51,694,280,280,280,280",
        "has_binding": false,
        "values": {
            "singular": "Pin album"
        }
    },
    "MessagePinFiles": {
        "url": "https://translations.telegram.org/en/android_x/general/MessagePinFiles",
        "photo_url": "https://telegra.ph/file/p/f6e3e2b5dac/b6cfaa8eeebdc4914174617.jpg?c=49,758,280,280,280,280",
        "has_binding": false,
        "values": {
            "singular": "Pin files"
        }
    },
    "MessagePinPlaylist": {
        "url": "https://translations.telegram.org/en/android_x/general/MessagePinPlaylist",
        "photo_url": "https://telegra.ph/file/p/19d0bc37718/6efb967241f20ab11ac3817.jpg?c=52,697,280,280,280,280",
        "has_binding": false,
        "values": {
            "singular": "Pin playlist"
        }
    },
    "MessageSeenNobody": {
        "url": "https://translations.telegram.org/en/android_x/general/MessageSeenNobody",
        "photo_url": "https://telegra.ph/file/p/8f2b8c10306/2910a7889545ea8228b0317.jpg?c=63,396,280,280,280,280",
        "has_binding": true,
        "values": {
            "singular": "Nobody Viewed"
        }
    },
    "MessageSeenPrivacy": {
        "url": "https://translations.telegram.org/en/android_x/general/MessageSeenPrivacy",
        "photo_url": "https://telegra.ph/file/p/a46b3d0f6df/7c833308efca676d5132017.jpg?c=0,587,585,588,278,280",
        "has_binding": true,
        "values": {
            "singular": "To protect privacy, views are only stored for 7 days."
        }
    },
    "MessageUnpinAlbum": {
        "url": "https://translations.telegram.org/en/android_x/general/MessageUnpinAlbum",
        "photo_url": "https://telegra.ph/file/p/49cfd54eae1/1046700cc82b45e9ee89e17.jpg?c=54,697,280,280,280,280",
        "has_binding": false,
        "values": {
            "singular": "Unpin album"
        }
    },
    "MessageUnpinFiles": {
        "url": "https://translations.telegram.org/en/android_x/general/MessageUnpinFiles",
        "photo_url": "https://telegra.ph/file/p/0926651a584/04e898573a40a6383cd8817.jpg?c=51,761,280,280,280,280",
        "has_binding": false,
        "values": {
            "singular": "Unpin files"
        }
    },
    "MessageUnpinPlaylist": {
        "url": "https://translations.telegram.org/en/android_x/general/MessageUnpinPlaylist",
        "photo_url": "https://telegra.ph/file/p/eb36a5b546a/330e89b13c53ad51c146d17.jpg?c=55,697,280,280,280,280",
        "has_binding": false,
        "values": {
            "singular": "Unpin playlist"
        }
    },
    "NoCloudThemeSupport": {
        "url": "https://translations.telegram.org/en/android_x/general/NoCloudThemeSupport",
        "photo_url": "https://telegra.ph/file/p/3b0dcf2b599/00d154b50ab32fe48134217.jpg?c=42,380,498,498,280,280",
        "has_binding": false,
        "values": {
            "singular": "This theme is not designed for **Telegram X**.<br/><br/>However, you may check for user-made themes in @tgx_perfection."
        }
    },
    "NoLocationAccessBackground": {
        "url": "https://translations.telegram.org/en/android_x/general/NoLocationAccessBackground",
        "photo_url": "https://telegra.ph/file/p/d00c94b3186/2e90a58fa82017f200bac17.jpg?c=42,330,508,508,280,280",
        "has_binding": false,
        "values": {
            "singular": "This feature requires access to your location while app is in background."
        }
    },
    "PrivateChat": {
        "url": "https://translations.telegram.org/en/android_x/general/PrivateChat",
        "photo_url": "https://telegra.ph/file/p/d754914b945/151067ad4959a4710f1d517.jpg?c=70,789,280,280,280,280",
        "has_binding": false,
        "values": {
            "singular": "Private Chat"
        }
    },
    "PrivateChatsMentions": {
        "url": "https://translations.telegram.org/en/android_x/general/PrivateChatsMentions",
        "photo_url": "https://telegra.ph/file/p/7c4e530fd05/a6ad47e327535a3b2161d17.jpg?c=56,152,490,490,280,280",
        "has_binding": false,
        "values": {
            "singular": "Private Chats and Mentions"
        }
    },
    "QDeleteCallFromRecent": {
        "url": "https://translations.telegram.org/en/android_x/general/QDeleteCallFromRecent",
        "photo_url": "https://telegra.ph/file/p/e760f59b510/e7757f8f2b5e68e56473b17.jpg?c=15,705,320,320,280,280",
        "has_binding": false,
        "values": {
            "singular": "Delete call from recents?"
        }
    },
    "QualityBetter": {
        "url": "https://translations.telegram.org/en/android_x/general/QualityBetter",
        "photo_url": "https://telegra.ph/file/p/1f0cbb36b81/1ff4ba86733cc540e141917.jpg?c=313,763,280,280,280,280",
        "has_binding": false,
        "values": {
            "singular": "Better quality"
        }
    },
    "QualityWorse": {
        "url": "https://translations.telegram.org/en/android_x/general/QualityWorse",
        "photo_url": "https://telegra.ph/file/p/1f0cbb36b81/1ff4ba86733cc540e141917.jpg?c=7,760,280,280,280,280",
        "has_binding": true,
        "values": {
            "singular": "Smaller size"
        }
    },
    "RecordingRound": {
        "url": "https://translations.telegram.org/en/android_x/general/RecordingRound",
        "photo_url": "https://telegra.ph/file/p/4ef8e998ab8/bcf55f1f2a057a6a181221d.jpg?c=220,23,280,280,280,280",
        "has_binding": true,
        "values": {
            "singular": "recording a video message"
        }
    },
    "RemindAtCustomTime": {
        "url": "https://translations.telegram.org/en/android_x/general/RemindAtCustomTime",
        "photo_url": "https://telegra.ph/file/p/17800eba226/84611859becd53624557d17.jpg?c=71,997,328,328,280,280",
        "has_binding": false,
        "values": {
            "singular": "Remind at specific date…"
        }
    },
    "RemindInXHours": {
        "url": "https://translations.telegram.org/en/android_x/general/RemindInXHours",
        "photo_url": "https://telegra.ph/file/p/17800eba226/84611859becd53624557d17.jpg?c=67,836,280,280,280,280",
        "has_binding": false,
        "values": {
            "singular": "Remind in <mark class=\"token\">%1$s</mark> hour",
            "plural": "Remind in <mark class=\"token\">%1$s</mark> hours"
        }
    },
    "RemindInXMinutes": {
        "url": "https://translations.telegram.org/en/android_x/general/RemindInXMinutes",
        "photo_url": "https://telegra.ph/file/p/17800eba226/84611859becd53624557d17.jpg?c=73,762,289,289,280,280",
        "has_binding": false,
        "values": {
            "singular": "Remind in <mark class=\"token\">%1$s</mark> minute",
            "plural": "Remind in <mark class=\"token\">%1$s</mark> minutes"
        }
    },
    "RemindInXYears": {
        "url": "https://translations.telegram.org/en/android_x/general/RemindInXYears",
        "photo_url": "https://telegra.ph/file/p/17800eba226/84611859becd53624557d17.jpg?c=65,976,280,280,280,280",
        "has_binding": false,
        "values": {
            "singular": "Remind in <mark class=\"token\">%1$s</mark> year",
            "plural": "Remind in <mark class=\"token\">%1$s</mark> years"
        }
    },
    "RepliesBot": {
        "url": "https://translations.telegram.org/en/android_x/general/RepliesBot",
        "photo_url": "https://telegra.ph/file/p/e5c6b549a68/2d201ec6416796afba66d17.jpg?c=116,1,280,280,280,280",
        "has_binding": true,
        "values": {
            "singular": "Replies"
        }
    },
    "ReplyNotifications": {
        "url": "https://translations.telegram.org/en/android_x/general/ReplyNotifications",
        "photo_url": "https://telegra.ph/file/p/e5c6b549a68/2d201ec6416796afba66d17.jpg?c=157,31,287,287,280,280",
        "has_binding": false,
        "values": {
            "singular": "comment notifications"
        }
    },
    "ReportChatPhoto": {
        "url": "https://translations.telegram.org/en/android_x/general/ReportChatPhoto",
        "photo_url": "https://telegra.ph/file/p/07069344a31/eb13c85f28c5428356d5117.jpg?c=10,408,371,371,280,280",
        "has_binding": false,
        "values": {
            "singular": "Report <mark class=\"token\">%1$s</mark>'s photo?"
        }
    },
    "SaveXToDownloads": {
        "url": "https://translations.telegram.org/en/android_x/general/SaveXToDownloads",
        "photo_url": null,
        "has_binding": false,
        "values": {
            "singular": "Save <mark class=\"token\">%1$s</mark> file to Downloads",
            "plural": "Save <mark class=\"token\">%1$s</mark> files to Downloads"
        }
    },
    "SaveXToMusic": {
        "url": "https://translations.telegram.org/en/android_x/general/SaveXToMusic",
        "photo_url": "https://telegra.ph/file/p/0eaea2ee5d0/48023c4d01447b7fc54e617.jpg?c=80,738,281,281,280,280",
        "has_binding": false,
        "values": {
            "singular": "Save <mark class=\"token\">%1$s</mark> file to Music",
            "plural": "Save <mark class=\"token\">%1$s</mark> files to Music"
        }
    },
    "SendInXYears": {
        "url": "https://translations.telegram.org/en/android_x/general/SendInXYears",
        "photo_url": "https://telegra.ph/file/p/fb9b11669f5/7f34e2b44391249ae866417.jpg?c=59,976,280,280,280,280",
        "has_binding": false,
        "values": {
            "singular": "Send in <mark class=\"token\">%1$s</mark> year",
            "plural": "Send in <mark class=\"token\">%1$s</mark> years"
        }
    },
    "SendLiveLocationInfo": {
        "url": "https://translations.telegram.org/en/android_x/general/SendLiveLocationInfo",
        "photo_url": "https://telegra.ph/file/p/c51c5f29f38/62fa444134f4ef65c18831d.jpg?c=124,706,456,456,280,280",
        "has_binding": true,
        "values": {
            "singular": "Updated in real time as you move"
        }
    },
    "SendXOriginals": {
        "url": "https://translations.telegram.org/en/android_x/general/SendXOriginals",
        "photo_url": "https://telegra.ph/file/p/c4f1e9167dc/ed7e732fb1f8bb061b27317.jpg?c=258,804,280,280,280,280",
        "has_binding": false,
        "values": {
            "singular": "Send <mark class=\"token\">%1$s</mark> original",
            "plural": "Send <mark class=\"token\">%1$s</mark> originals"
        }
    },
    "ShareFolder": {
        "url": "https://translations.telegram.org/en/android_x/general/ShareFolder",
        "photo_url": "https://telegra.ph/file/p/2c2494b4542/7f32971c5e6b67d60092117.jpg?c=72,56,280,280,280,280",
        "has_binding": false,
        "values": {
            "singular": "Share Folder"
        }
    },
    "ShareTextChat": {
        "url": "https://translations.telegram.org/en/android_x/general/ShareTextChat",
        "photo_url": "https://telegra.ph/file/p/59171536fac/88f7bbbd8cff396fd251e1d.jpg?c=87,209,485,485,280,280",
        "has_binding": false,
        "values": {
            "singular": "\"<mark class=\"token\">%1$s</mark>\"'s chat photo"
        }
    },
    "ShareTextChatLink": {
        "url": "https://translations.telegram.org/en/android_x/general/ShareTextChatLink",
        "photo_url": "https://telegra.ph/file/p/238905d8598/dafd300636a1b5d5da23b1d.jpg?c=90,675,588,588,280,280",
        "has_binding": false,
        "values": {
            "singular": "Join \"<mark class=\"token\">%1$s</mark>\" on Telegram: <mark class=\"token\">%2$s</mark>"
        }
    },
    "ShareTextMyLink2": {
        "url": "https://translations.telegram.org/en/android_x/general/ShareTextMyLink2",
        "photo_url": "https://telegra.ph/file/p/1b0f5b08b8a/f7387f28553963052946417.jpg?c=83,593,370,370,280,280",
        "has_binding": false,
        "values": {
            "singular": "My Telegram link: <mark class=\"token\">%1$s</mark>"
        }
    },
    "ShareTextStickerLink": {
        "url": "https://translations.telegram.org/en/android_x/general/ShareTextStickerLink",
        "photo_url": "https://telegra.ph/file/p/5dcc5ceb39b/87abe955725d0e26055b51d.jpg?c=48,393,735,735,280,280",
        "has_binding": false,
        "values": {
            "singular": "Check out \"<mark class=\"token\">%1$s</mark>\" sticker set for Telegram: <mark class=\"token\">%2$s</mark>"
        }
    },
    "ShareTextStickerLink2": {
        "url": "https://translations.telegram.org/en/android_x/general/ShareTextStickerLink2",
        "photo_url": "https://telegra.ph/file/p/9a9817af972/f98dda2f27bea100029ec1d.jpg?c=48,508,728,728,280,280",
        "has_binding": false,
        "values": {
            "singular": "Check out \"<mark class=\"token\">%1$s</mark>\" sticker set: <mark class=\"token\">%2$s</mark>"
        }
    },
    "SwipeToSwapLinkPreview": {
        "url": "https://translations.telegram.org/en/android_x/general/SwipeToSwapLinkPreview",
        "photo_url": "https://telegra.ph/file/p/25b06e06c95/0fa03ae7bd9bc7f0552af17.jpg?c=105,654,431,431,280,280",
        "has_binding": false,
        "values": {
            "singular": "Swipe to choose specific link preview"
        }
    },
    "TapToSelectLanguage": {
        "url": "https://translations.telegram.org/en/android_x/general/TapToSelectLanguage",
        "photo_url": "https://telegra.ph/file/p/1d6d902faeb/9dd90ae5713150caf271817.jpg?c=16,326,280,280,280,280",
        "has_binding": false,
        "values": {
            "singular": "Tap to select language"
        }
    },
    "TextFormatting": {
        "url": "https://translations.telegram.org/en/android_x/general/TextFormatting",
        "photo_url": "https://telegra.ph/file/p/189f5968b06/3656a6f150276ae58826b17.jpg?c=16,693,280,280,280,280",
        "has_binding": false,
        "values": {
            "singular": "Text formatting"
        }
    },
    "TextFormattingTools": {
        "url": "https://translations.telegram.org/en/android_x/general/TextFormattingTools",
        "photo_url": "https://telegra.ph/file/p/189f5968b06/3656a6f150276ae58826b17.jpg?c=12,799,280,280,280,280",
        "has_binding": false,
        "values": {
            "singular": "Tools"
        }
    },
    "TextFormattingTranslate": {
        "url": "https://translations.telegram.org/en/android_x/general/TextFormattingTranslate",
        "photo_url": "https://telegra.ph/file/p/189f5968b06/3656a6f150276ae58826b17.jpg?c=178,799,280,280,280,280",
        "has_binding": false,
        "values": {
            "singular": "Translate"
        }
    },
    "ThisChatCantBeShared": {
        "url": "https://translations.telegram.org/en/android_x/general/ThisChatCantBeShared",
        "photo_url": "https://telegra.ph/file/p/2c774b3de82/a38c1181778a0d42c71f217.jpg?c=12,477,280,280,280,280",
        "has_binding": false,
        "values": {
            "singular": "This chat can’t be shared"
        }
    },
    "TransferOwnershipSecurityAlert": {
        "url": "https://translations.telegram.org/en/android_x/general/TransferOwnershipSecurityAlert",
        "photo_url": "https://telegra.ph/file/p/deffd032512/46edacc21ee16fee5387717.jpg?c=9,679,280,280,280,280",
        "has_binding": true,
        "values": {
            "singular": "Security Check"
        }
    },
    "TransferOwnershipSecurityWaitSession": {
        "url": "https://translations.telegram.org/en/android_x/general/TransferOwnershipSecurityWaitSession",
        "photo_url": "https://telegra.ph/file/p/deffd032512/46edacc21ee16fee5387717.jpg?c=0,516,587,590,278,280",
        "has_binding": false,
        "values": {
            "singular": "Sorry, but you need to wait **<mark class=\"token\">%1$s</mark>** before you can transfer ownership, because you've signed in on the current device just recently."
        }
    },
    "Translate": {
        "url": "https://translations.telegram.org/en/android_x/general/Translate",
        "photo_url": "https://telegra.ph/file/p/c231256ab74/62bd26c23659669f0460c17.jpg?c=53,873,280,280,280,280",
        "has_binding": true,
        "values": {
            "singular": "Translate"
        }
    },
    "TranslateLangUnknown": {
        "url": "https://translations.telegram.org/en/android_x/general/TranslateLangUnknown",
        "photo_url": "https://telegra.ph/file/p/f5d3cf6878a/80146145eeeecb45556fe17.jpg?c=247,919,280,280,280,280",
        "has_binding": false,
        "values": {
            "singular": "Unknown"
        }
    },
    "TranslateOff": {
        "url": "https://translations.telegram.org/en/android_x/general/TranslateOff",
        "photo_url": "https://telegra.ph/file/p/f5237899750/b1cdb213d7bb5c58bf49217.jpg?c=68,873,280,280,280,280",
        "has_binding": false,
        "values": {
            "singular": "Disable translation"
        }
    },
    "TranslateOriginal": {
        "url": "https://translations.telegram.org/en/android_x/general/TranslateOriginal",
        "photo_url": "https://telegra.ph/file/p/1d6d902faeb/9dd90ae5713150caf271817.jpg?c=58,394,280,280,280,280",
        "has_binding": false,
        "values": {
            "singular": "Original message"
        }
    },
    "TranslateWait": {
        "url": "https://translations.telegram.org/en/android_x/general/TranslateWait",
        "photo_url": "https://telegra.ph/file/p/e0aa5bebd8b/762853a071e19d09c899b17.jpg?c=53,392,280,280,280,280",
        "has_binding": false,
        "values": {
            "singular": "Please wait…"
        }
    },
    "TranslatedFrom": {
        "url": "https://translations.telegram.org/en/android_x/general/TranslatedFrom",
        "photo_url": "https://telegra.ph/file/p/35a4b711baf/cac30c37401fe2d7da4f017.jpg?c=68,394,280,280,280,280",
        "has_binding": false,
        "values": {
            "singular": "Translated from <mark class=\"token\">%1$s</mark>"
        }
    },
    "TranslatingTo": {
        "url": "https://translations.telegram.org/en/android_x/general/TranslatingTo",
        "photo_url": "https://telegra.ph/file/p/e0aa5bebd8b/762853a071e19d09c899b17.jpg?c=64,345,344,344,280,280",
        "has_binding": false,
        "values": {
            "singular": "Translating to <mark class=\"token\">%1$s</mark>"
        }
    },
    "TranslationCopy": {
        "url": "https://translations.telegram.org/en/android_x/general/TranslationCopy",
        "photo_url": "https://telegra.ph/file/p/becb4f53ae1/508cee20f0a71749d4b9117.jpg?c=64,808,280,280,280,280",
        "has_binding": true,
        "values": {
            "singular": "Copy translation"
        }
    },
    "UnpinAll": {
        "url": "https://translations.telegram.org/en/android_x/general/UnpinAll",
        "photo_url": "https://telegra.ph/file/p/958f59b570c/fcf68278248f8561eed3d17.jpg?c=151,868,300,300,280,280",
        "has_binding": true,
        "values": {
            "singular": "Unpin All Messages"
        }
    },
    "UnpinMessagesConfirm": {
        "url": "https://translations.telegram.org/en/android_x/general/UnpinMessagesConfirm",
        "photo_url": "https://telegra.ph/file/p/9114937d60b/659b6333f307d4d1a59fa17.jpg?c=46,761,280,280,280,280",
        "has_binding": false,
        "values": {
            "singular": "Unpin"
        }
    },
    "UnpinXMessages": {
        "url": "https://translations.telegram.org/en/android_x/general/UnpinXMessages",
        "photo_url": "https://telegra.ph/file/p/9114937d60b/659b6333f307d4d1a59fa17.jpg?c=11,707,280,280,280,280",
        "has_binding": false,
        "values": {
            "singular": "Unpin <mark class=\"token\">%1$s</mark> message?",
            "plural": "Unpin <mark class=\"token\">%1$s</mark> messages?"
        }
    },
    "UpdateSourceChanges": {
        "url": "https://translations.telegram.org/en/android_x/general/UpdateSourceChanges",
        "photo_url": "https://telegra.ph/file/p/46b196cc4ce/6fc59afc99c327359839e17.jpg?c=72,724,382,382,280,280",
        "has_binding": false,
        "values": {
            "singular": "View source code changes"
        }
    },
    "VoipDeclined": {
        "url": "https://translations.telegram.org/en/android_x/general/VoipDeclined",
        "photo_url": "https://telegra.ph/file/p/dfc87cc8591/9fe0f265a1d533daca6261d.jpg?c=187,94,280,280,280,280",
        "has_binding": false,
        "values": {
            "singular": "Call canceled"
        }
    },
    "VoipOfflineAirplane": {
        "url": "https://translations.telegram.org/en/android_x/general/VoipOfflineAirplane",
        "photo_url": "https://telegra.ph/file/p/26cd2282a76/bc2b58d257acf2840be771d.jpg?c=42,314,675,675,280,280",
        "has_binding": true,
        "values": {
            "singular": "You have airplane mode enabled. Please turn it off or connect to Wi-Fi to make calls."
        }
    },
    "XFoundMessagesFromChat": {
        "url": "https://translations.telegram.org/en/android_x/general/XFoundMessagesFromChat",
        "photo_url": "https://telegra.ph/file/p/69f5bc17765/539f82f127c14566a941d17.jpg?c=124,46,390,390,280,280",
        "has_binding": false,
        "values": {
            "singular": "<mark class=\"token\">%1$s</mark> message from <mark class=\"token\">%2$s</mark>",
            "plural": "<mark class=\"token\">%1$s</mark> messages from <mark class=\"token\">%2$s</mark>"
        }
    },
    "XGifSaved": {
        "url": "https://translations.telegram.org/en/android_x/general/XGifSaved",
        "photo_url": "https://telegra.ph/file/p/9221eacae20/a42b772a76f93222be7d417.jpg?c=76,732,471,471,280,280",
        "has_binding": false,
        "values": {
            "singular": "<mark class=\"token\">%1$s</mark> new GIF available in the media keyboard",
            "plural": "<mark class=\"token\">%1$s</mark> new GIFs available in the media keyboard"
        }
    },
    "XPinnedMessages": {
        "url": "https://translations.telegram.org/en/android_x/general/XPinnedMessages",
        "photo_url": "https://telegra.ph/file/p/958f59b570c/fcf68278248f8561eed3d17.jpg?c=125,49,280,280,280,280",
        "has_binding": false,
        "values": {
            "singular": "<mark class=\"token\">%1$s</mark> pinned message",
            "plural": "<mark class=\"token\">%1$s</mark> pinned messages"
        }
    },
    "XSetAutoDeleteSeconds": {
        "url": "https://translations.telegram.org/en/android_x/general/XSetAutoDeleteSeconds",
        "photo_url": "https://telegra.ph/file/p/84b654fef05/b4ea2e3f2d649957bb5c117.jpg?c=0,398,600,638,262,280",
        "has_binding": false,
        "values": {
            "singular": "<mark class=\"token\">%2$s</mark> set messages to auto-delete in <mark class=\"token\">%1$s</mark> second",
            "plural": "<mark class=\"token\">%2$s</mark> set messages to auto-delete in <mark class=\"token\">%1$s</mark> seconds"
        }
    },
    "email_LoginHelp": {
        "url": "https://translations.telegram.org/en/android_x/general/email_LoginHelp",
        "photo_url": "https://telegra.ph/file/p/8e107a7d9db/05242686bed8c1e88078d17.jpg?c=112,133,280,280,280,280",
        "has_binding": false,
        "values": {
            "singular": "recover@telegram.org"
        }
    },
    "error_BOTS_TOO_MUCH": {
        "url": "https://translations.telegram.org/en/android_x/general/error_BOTS_TOO_MUCH",
        "photo_url": null,
        "has_binding": true,
        "values": {
            "singular": "There are too many bots in this group. Please remove some of the bots you're not using first."
        }
    },
    "error_INVITES_TOO_MUCH": {
        "url": "https://translations.telegram.org/en/android_x/general/error_INVITES_TOO_MUCH",
        "photo_url": "https://telegra.ph/file/p/a67748f3a04/2c57d78b7f73578a8411c17.jpg?c=102,844,435,435,280,280",
        "has_binding": false,
        "values": {
            "singular": "Sorry, you have too many invite links."
        }
    },
    "locationUpdated_date": {
        "url": "https://translations.telegram.org/en/android_x/general/locationUpdated_date",
        "photo_url": "https://telegra.ph/file/p/fcce9648e0e/9b269ab1b514eb19e4b7b17.jpg?c=91,825,354,354,280,280",
        "has_binding": false,
        "values": {
            "singular": "updated on <mark class=\"token\">%1$s</mark> at <mark class=\"token\">%2$s</mark>"
        }
    },
    "locationUpdated_hours": {
        "url": "https://translations.telegram.org/en/android_x/general/locationUpdated_hours",
        "photo_url": "https://telegra.ph/file/p/12f8c016a37/5557616f66f747cc81e0b17.jpg?c=83,893,280,280,280,280",
        "has_binding": true,
        "values": {
            "singular": "updated <mark class=\"token\">%1$s</mark> hour ago",
            "plural": "updated <mark class=\"token\">%1$s</mark> hours ago"
        }
    },
    "locationUpdated_minutes": {
        "url": "https://translations.telegram.org/en/android_x/general/locationUpdated_minutes",
        "photo_url": "https://telegra.ph/file/p/3c84bf15032/a17636709676e675ed38817.jpg?c=94,893,280,280,280,280",
        "has_binding": false,
        "values": {
            "singular": "updated <mark class=\"token\">%1$s</mark> minute ago",
            "plural": "updated <mark class=\"token\">%1$s</mark> minutes ago"
        }
    },
    "locationUpdated_now": {
        "url": "https://translations.telegram.org/en/android_x/general/locationUpdated_now",
        "photo_url": "https://telegra.ph/file/p/778df3aa06b/524680192837099a12d7917.jpg?c=79,893,280,280,280,280",
        "has_binding": true,
        "values": {
            "singular": "updated just now"
        }
    },
    "locationUpdated_weekday": {
        "url": "https://translations.telegram.org/en/android_x/general/locationUpdated_weekday",
        "photo_url": "https://telegra.ph/file/p/f5b343c5b17/bbfdc270a31471d9fcddf17.jpg?c=93,893,280,280,280,280",
        "has_binding": false,
        "values": {
            "singular": "updated on <mark class=\"token\">%1$s</mark> at <mark class=\"token\">%2$s</mark>"
        }
    },
    "locationUpdated_yesterday": {
        "url": "https://translations.telegram.org/en/android_x/general/locationUpdated_yesterday",
        "photo_url": "https://telegra.ph/file/p/22bbc920423/190871bcb0ae41c94e28817.jpg?c=96,893,280,280,280,280",
        "has_binding": true,
        "values": {
            "singular": "updated yesterday at <mark class=\"token\">%1$s</mark>"
        }
    },
    "mentionCount": {
        "url": "https://translations.telegram.org/en/android_x/general/mentionCount",
        "photo_url": "https://telegra.ph/file/p/07c857f6ca8/84bf3864b544d21977ef417.jpg?c=173,0,280,275,280,274",
        "has_binding": false,
        "values": {
            "singular": "<mark class=\"token\">%1$s</mark> mention",
            "plural": "<mark class=\"token\">%1$s</mark> mentions"
        }
    },
    "message_edited_date": {
        "url": "https://translations.telegram.org/en/android_x/general/message_edited_date",
        "photo_url": "https://telegra.ph/file/p/b8251eb0d09/e08dddae07d89faddd7f317.jpg?c=221,812,302,302,280,280",
        "has_binding": false,
        "values": {
            "singular": "Edited on <mark class=\"token\">%1$s</mark> at <mark class=\"token\">%2$s</mark>"
        }
    },
    "message_edited_hours": {
        "url": "https://translations.telegram.org/en/android_x/general/message_edited_hours",
        "photo_url": "https://telegra.ph/file/p/aec592cac11/5d37919c427c38a5e1c1d17.jpg?c=199,768,280,280,280,280",
        "has_binding": false,
        "values": {
            "singular": "Edited <mark class=\"token\">%1$s</mark> hour ago",
            "plural": "Edited <mark class=\"token\">%1$s</mark> hours ago"
        }
    },
    "message_edited_minutes": {
        "url": "https://translations.telegram.org/en/android_x/general/message_edited_minutes",
        "photo_url": "https://telegra.ph/file/p/a91e2da47e1/559221f6b79707407db3c17.jpg?c=201,767,280,280,280,280",
        "has_binding": false,
        "values": {
            "singular": "Edited <mark class=\"token\">%1$s</mark> minute ago",
            "plural": "Edited <mark class=\"token\">%1$s</mark> minutes ago"
        }
    },
    "message_edited_now": {
        "url": "https://translations.telegram.org/en/android_x/general/message_edited_now",
        "photo_url": "https://telegra.ph/file/p/928d275779f/650f2c66cc2521920fa3f17.jpg?c=197,766,280,280,280,280",
        "has_binding": false,
        "values": {
            "singular": "Edited just now"
        }
    },
    "message_edited_today": {
        "url": "https://translations.telegram.org/en/android_x/general/message_edited_today",
        "photo_url": "https://telegra.ph/file/p/983876fd8a8/a1b24abe09f25c5f4aa2717.jpg?c=202,766,280,280,280,280",
        "has_binding": false,
        "values": {
            "singular": "Edited today at <mark class=\"token\">%1$s</mark>"
        }
    },
    "message_edited_weekday": {
        "url": "https://translations.telegram.org/en/android_x/general/message_edited_weekday",
        "photo_url": "https://telegra.ph/file/p/641325202e3/46ba632c08744981072a317.jpg?c=204,596,280,280,280,280",
        "has_binding": false,
        "values": {
            "singular": "Edited on <mark class=\"token\">%1$s</mark> at <mark class=\"token\">%2$s</mark>"
        }
    },
    "message_edited_yesterday": {
        "url": "https://translations.telegram.org/en/android_x/general/message_edited_yesterday",
        "photo_url": "https://telegra.ph/file/p/6e7f6dda82c/56475ac67d5df716d0f1b17.jpg?c=196,754,296,296,280,280",
        "has_binding": false,
        "values": {
            "singular": "Edited yesterday at <mark class=\"token\">%1$s</mark>"
        }
    },
    "status_LastSeenRecently": {
        "url": "https://translations.telegram.org/en/android_x/general/status_LastSeenRecently",
        "photo_url": "https://telegra.ph/file/p/63668df278a/1fb801824902a43c07fba19.jpg?c=287,58,397,397,280,280",
        "has_binding": true,
        "values": {
            "singular": "last seen recently"
        }
    },
    "url_translationsPrefix": {
        "url": "https://translations.telegram.org/en/android_x/general/url_translationsPrefix",
        "photo_url": null,
        "has_binding": false,
        "values": {
            "singular": "https://translations.telegram.org/en/android_x/unsorted/"
        }
    },
    "xChatsAlreadyJoined": {
        "url": "https://translations.telegram.org/en/android_x/general/xChatsAlreadyJoined",
        "photo_url": "https://telegra.ph/file/p/f7168df461d/ae0de641450e8e04c5ed817.jpg?c=12,305,280,280,280,280",
        "has_binding": false,
        "values": {
            "singular": "<mark class=\"token\">%1$s</mark> chat already joined",
            "plural": "<mark class=\"token\">%1$s</mark> chats already joined"
        }
    },
    "xChatsToJoin": {
        "url": "https://translations.telegram.org/en/android_x/general/xChatsToJoin",
        "photo_url": "https://telegra.ph/file/p/4d73c687cb6/b42bf9977308d8765bfca17.jpg?c=10,118,280,280,280,280",
        "has_binding": false,
        "values": {
            "singular": "<mark class=\"token\">%1$s</mark> chat to join",
            "plural": "<mark class=\"token\">%1$s</mark> chats to join"
        }
    },
    "xChatsToLeave": {
        "url": "https://translations.telegram.org/en/android_x/general/xChatsToLeave",
        "photo_url": "https://telegra.ph/file/p/2594b1c5b7e/0a5a884244a79cf5c159417.jpg?c=10,117,280,280,280,280",
        "has_binding": false,
        "values": {
            "singular": "<mark class=\"token\">%1$s</mark> chat to leave",
            "plural": "<mark class=\"token\">%1$s</mark> chats to leave"
        }
    },
    "xGiveawayWinnersCountMore": {
        "url": "https://translations.telegram.org/en/android_x/general/xGiveawayWinnersCountMore",
        "photo_url": "https://telegra.ph/file/p/c8e8ba381de/fb876e38f930eee57a18917.jpg?c=175,815,280,280,280,280",
        "has_binding": false,
        "values": {
            "singular": "and <mark class=\"token\">%1$s</mark> more.",
            "plural": "and <mark class=\"token\">%1$s</mark> more."
        }
    },
    "xMessages": {
        "url": "https://translations.telegram.org/en/android_x/general/xMessages",
        "photo_url": "https://telegra.ph/file/p/df70937c5c8/eb0a8593c73a00960def61d.jpg?c=206,12,280,280,280,280",
        "has_binding": false,
        "values": {
            "singular": "<mark class=\"token\">%1$s</mark> message",
            "plural": "<mark class=\"token\">%1$s</mark> messages"
        }
    },
    "xOfYChatsSelected": {
        "url": "https://translations.telegram.org/en/android_x/general/xOfYChatsSelected",
        "photo_url": "https://telegra.ph/file/p/2c2494b4542/7f32971c5e6b67d60092117.jpg?c=11,393,280,280,280,280",
        "has_binding": false,
        "values": {
            "singular": "<mark class=\"token\">%1$d</mark>/<mark class=\"token\">%2$d</mark> chats selected"
        }
    }
}